{
    "general": {
        "ip": "",
        "persistent": "arakoon",
        "volatile": "memcache",
        "audittrails": 30,
        "configdir": "/opt/OpenvStorage/config"
    },
    "broker": {
        "protocol": "amqp",
        "login": "ovs",
        "password": "0penv5tor4ge",
        "port": 5672,
        "queues": {
            "storagedriver": "volumerouter"
        }
    },
    "storagedriver": {
        "mds": {
            "safety": 3,
            "maxload": 75,
            "tlogs": 100
        }
    },
    "webapps": {
        "django": {
            "uiname": "api",
            "appname": "api",
            "dir": "webapp",
            "name": "CloudFounders Engineering Dept.",
            "email": "engineering@cloudfounders.com",
            "dbname": "api.sqlite3",
            "secret": "pl4c3h0ld3r"
        }
    },
    "support": {
        "enabled": false,
        "cid": "",
        "nid": "",
        "enablesupport": false,
        "interval": 60
    },
    "ports": {
        "storagedriver": [[26200, 26299]],
        "mds": [[26300, 26399]],
        "arakoon": [8870]
    },
    "logging": {
        "level": "DEBUG",
        "path": "/var/log/ovs",
        "defaultfile": "generic",
        "defaultname": "logger"
    },
    "plugins": {
        "generic": [],
        "backends": []
    }
}
